retinalysis_fundusprep-0.5.3.dist-info/licenses/LICENSE
rtnls_fundusprep/__init__.py
rtnls_fundusprep/cfi_bounds.py
rtnls_fundusprep/circle_fit.py
rtnls_fundusprep/cli.py
rtnls_fundusprep/mask_extraction.py
rtnls_fundusprep/preprocessor.py
rtnls_fundusprep/transformation.py
rtnls_fundusprep/utils.py
retinalysis_fundusprep-0.5.3.dist-info/METADATA
retinalysis_fundusprep-0.5.3.dist-info/WHEEL
retinalysis_fundusprep-0.5.3.dist-info/entry_points.txt
retinalysis_fundusprep-0.5.3.dist-info/top_level.txt
retinalysis_fundusprep-0.5.3.dist-info/RECORD
