Metadata-Version: 2.4
Name: retinalysis-fundusprep
Version: 0.5.3
Summary: Easy, robust CFI bounds detection and contrast enhancement
Author-email: Bart Liefers <your.email@example.com>
License:                     GNU AFFERO GENERAL PUBLIC LICENSE
Project-URL: Homepage, https://github.com/Eyened/retinalysis-fundusprep
Project-URL: Bug Tracker, https://github.com/Eyened/retinalysis-fundusprep/issues
Requires-Python: <3.13,>=3.10
License-File: LICENSE
Requires-Dist: numpy==2.*
Requires-Dist: pandas==2.*
Requires-Dist: scikit-learn==1.*
Requires-Dist: scikit-image==0.24.0
Requires-Dist: opencv-python==4.*
Requires-Dist: matplotlib==3.*
Requires-Dist: joblib==1.*
Requires-Dist: tqdm==4.*
Requires-Dist: Pillow==11.*
Requires-Dist: click==8.*
Requires-Dist: pydicom==3.*
Dynamic: license-file
